sgflib/__init__.py
sgflib/board.py
sgflib/collection.py
sgflib/cursor.py
sgflib/enums.py
sgflib/exceptions.py
sgflib/game_tree.py
sgflib/kifu.py
sgflib/node.py
sgflib/parser.py
sgflib/property_value.py
sgflib/sequence.py
sgflib/types.py
sgflib/utils.py
sgflib-0.1.0.dist-info/LICENSE
sgflib-0.1.0.dist-info/WHEEL
sgflib-0.1.0.dist-info/METADATA
sgflib-0.1.0.dist-info/RECORD
