Metadata-Version: 2.1
Name: sgflib
Version: 0.1.0
Summary: SGF library
Author: Oleksandr Hiliazov
Author-email: oleksandr.hiliazov@gmail.com
Requires-Python: >=3.8,<4.0
Classifier: Programming Language :: Python :: 3
Classifier: Programming Language :: Python :: 3.10
Classifier: Programming Language :: Python :: 3.8
Classifier: Programming Language :: Python :: 3.9
Requires-Dist: coverage (>=6.4.1,<7.0.0)
Requires-Dist: pydantic (>=1.9.1,<2.0.0)
